hypnobox/__init__.py
hypnobox/admin.py
hypnobox/forms.py
hypnobox/models.py
hypnobox/settings.py
hypnobox/specs.py
hypnobox/urls.py
hypnobox/views.py
hypnobox/locale/pt_BR/LC_MESSAGES/django.po
hypnobox/migrations/0001_initial.py
hypnobox/migrations/0002_auto_20160909_1835.py
hypnobox/migrations/0003_auto_20160913_1040.py
hypnobox/migrations/0004_lead_product_description.py
hypnobox/migrations/0005_auto_20161121_1735.py
hypnobox/migrations/__init__.py
hypnobox/templates/hypnobox/_link.html
hypnobox/templates/hypnobox/base.html
hypnobox/templates/hypnobox/lead_form.html
hypnobox/templatetags/__init__.py
hypnobox/templatetags/hypnobox_tags.py
hypnobox_django-0.4.1.dist-info/DESCRIPTION.rst
hypnobox_django-0.4.1.dist-info/METADATA
hypnobox_django-0.4.1.dist-info/RECORD
hypnobox_django-0.4.1.dist-info/WHEEL
hypnobox_django-0.4.1.dist-info/metadata.json
hypnobox_django-0.4.1.dist-info/top_level.txt
