Metadata-Version: 2.0
Name: hypnobox-django
Version: 0.4.1
Summary: Integrate your site with Hypnobox Chat Service.
Home-page: https://github.com/fgmacedo/hypnobox-django
Author: Fernando Macedo
Author-email: fgmacedo@gmail.com
License: MIT
Keywords: hypnobox-django
Platform: UNKNOWN
Classifier: Development Status :: 3 - Alpha
Classifier: Framework :: Django
Classifier: Framework :: Django :: 1.9
Classifier: Intended Audience :: Developers
Classifier: License :: OSI Approved :: MIT License
Classifier: Natural Language :: English
Classifier: Programming Language :: Python :: 2
Classifier: Programming Language :: Python :: 2.7
Classifier: Programming Language :: Python :: 3
Classifier: Programming Language :: Python :: 3.4
Classifier: Programming Language :: Python :: 3.5
Requires-Dist: requests (>=2.0.0)
